djnotty
