Metadata-Version: 1.0
Name: djnotty
Version: 0.0.5
Summary: Create popup notifications.
Home-page: http://git.dvebukvy.ru:9852/xacce/djnotty
Author: xacce
Author-email: UNKNOWN
License: MIT
Platform: UNKNOWN
